openredirect/__init__.py
openredirect/main.py
openredirect/includes/__init__.py
openredirect/includes/keys.py
openredirect/includes/readfile.py
openredirect/includes/scan.py
openredirect/includes/sms.py
openredirect/includes/writing.py
openredirect/utils/__init__.py
openredirect/utils/banner.py
openredirect/utils/check_inter.py
openredirect_checker-0.0.1.dist-info/LICENSE
openredirect_checker-0.0.1.dist-info/METADATA
openredirect_checker-0.0.1.dist-info/WHEEL
openredirect_checker-0.0.1.dist-info/entry_points.txt
openredirect_checker-0.0.1.dist-info/top_level.txt
openredirect_checker-0.0.1.dist-info/RECORD
