Metadata-Version: 2.1
Name: openredirect-checker
Version: 0.0.1
Author: @TENET_B2H
Author-email: <tenet@gmail.com>
Classifier: Development Status :: 1 - Planning
Classifier: Intended Audience :: Developers
Classifier: Programming Language :: Python :: 3
Classifier: Operating System :: Unix
Classifier: Operating System :: MacOS :: MacOS X
Classifier: Operating System :: Microsoft :: Windows
License-File: LICENSE
Requires-Dist: urllib3
Requires-Dist: requests
